capsnet_tf1/__init__.py
capsnet_tf1/layers.py
capsnet_tf1/losses.py
capsnet_tf1/models.py
capsnet_tf1/setup.py
capsnet_tf1/utils.py
capsnet_tf2/__init__.py
capsnet_tf2/layers.py
capsnet_tf2/losses.py
capsnet_tf2/models.py
capsnet_tf2/setup.py
capsnet_tf2/utils.py
datasets/__init__.py
datasets/setup.py
datasets/ucf101.py
datasets/ucf50.py
datasets/utils.py
dynamic_images/__init__.py
dynamic_images/setup.py
dynamic_images/utils.py
hexucf-0.0.9a0.dist-info/METADATA
hexucf-0.0.9a0.dist-info/WHEEL
hexucf-0.0.9a0.dist-info/top_level.txt
hexucf-0.0.9a0.dist-info/RECORD
