Metadata-Version: 2.1
Name: hexucf
Version: 0.0.9a0
Summary: UCF Dataset
Home-page: UNKNOWN
Author: Vladislav Ovchinnikov
Author-email: vladovchinnikov950@gmail.com
License: MIT
Keywords: ucf ai datasets
Platform: UNKNOWN
Classifier: Development Status :: 3 - Alpha
Classifier: License :: OSI Approved :: MIT License
Classifier: Programming Language :: Python :: 3.6
Requires-Dist: patool
Requires-Dist: pandas
Requires-Dist: Pillow
Requires-Dist: opencv-python
Requires-Dist: numpy
Requires-Dist: hex-dynamic-images
